NOSMaker/__init__.py
NOSMaker-0.1.dist-info/LICENSE
NOSMaker-0.1.dist-info/METADATA
NOSMaker-0.1.dist-info/WHEEL
NOSMaker-0.1.dist-info/top_level.txt
NOSMaker-0.1.dist-info/RECORD
