Metadata-Version: 2.1
Name: NOSMaker
Version: 0.1
Summary: Package Description
Home-page: http://0nera.github.io/NOSMaker
License: UNKNOWN
Platform: UNKNOWN
License-File: LICENSE
